p2smi/__init__.py
p2smi/chemMods.py
p2smi/chemProps.py
p2smi/fasta2smi.py
p2smi/genPeps.py
p2smi/synthRules.py
p2smi/utilities/__init__.py
p2smi/utilities/aminoacids.py
p2smi/utilities/smilesgen.py
p2smi-1.1.1.dist-info/licenses/LICENSE
p2smi-1.1.1.dist-info/METADATA
p2smi-1.1.1.dist-info/WHEEL
p2smi-1.1.1.dist-info/entry_points.txt
p2smi-1.1.1.dist-info/top_level.txt
p2smi-1.1.1.dist-info/RECORD
