Metadata-Version: 2.4
Name: p2smi
Version: 1.1.1
Summary: A toolkit enabling SMILES generation and property analysis for noncanonical and cyclized peptides.
Home-page: https://github.com/AaronFeller/p2smi
Author: Aaron L. Feller
Author-email: Aaron Feller <aaronleefeller@gmail.com>
License: MIT
Requires-Python: >=3.9
License-File: LICENSE
Requires-Dist: rdkit
Requires-Dist: numpy
Provides-Extra: dev
Requires-Dist: pytest; extra == "dev"
Requires-Dist: black; extra == "dev"
Requires-Dist: flake8; extra == "dev"
Requires-Dist: pytest-cov; extra == "dev"
Requires-Dist: pre-commit; extra == "dev"
Dynamic: license-file
